odoo/addons/fieldservice_calendar/README.rst
odoo/addons/fieldservice_calendar/__init__.py
odoo/addons/fieldservice_calendar/__manifest__.py
odoo/addons/fieldservice_calendar/i18n/es_AR.po
odoo/addons/fieldservice_calendar/i18n/fieldservice_calendar.pot
odoo/addons/fieldservice_calendar/i18n/fr.po
odoo/addons/fieldservice_calendar/i18n/it.po
odoo/addons/fieldservice_calendar/i18n/pt_BR.po
odoo/addons/fieldservice_calendar/models/__init__.py
odoo/addons/fieldservice_calendar/models/calendar.py
odoo/addons/fieldservice_calendar/models/fsm_order.py
odoo/addons/fieldservice_calendar/models/fsm_team.py
odoo/addons/fieldservice_calendar/readme/CONFIGURE.rst
odoo/addons/fieldservice_calendar/readme/CONTRIBUTORS.rst
odoo/addons/fieldservice_calendar/readme/DESCRIPTION.rst
odoo/addons/fieldservice_calendar/static/description/icon.png
odoo/addons/fieldservice_calendar/static/description/index.html
odoo/addons/fieldservice_calendar/tests/__init__.py
odoo/addons/fieldservice_calendar/tests/test_fsm_calendar.py
odoo/addons/fieldservice_calendar/views/fsm_order.xml
odoo/addons/fieldservice_calendar/views/fsm_team.xml
odoo12_addon_fieldservice_calendar-12.0.1.0.0.99.dev8.dist-info/METADATA
odoo12_addon_fieldservice_calendar-12.0.1.0.0.99.dev8.dist-info/WHEEL
odoo12_addon_fieldservice_calendar-12.0.1.0.0.99.dev8.dist-info/top_level.txt
odoo12_addon_fieldservice_calendar-12.0.1.0.0.99.dev8.dist-info/RECORD
