Metadata-Version: 2.1
Name: odoo12-addon-fieldservice_calendar
Version: 12.0.1.0.0.99.dev8
Summary: Add calendar to FSM Orders
Home-page: https://github.com/OCA/field-service
Author: Akretion, Odoo Community Association (OCA)
Author-email: support@odoo-community.org
License: AGPL-3
Classifier: Programming Language :: Python
Classifier: Framework :: Odoo
Classifier: Framework :: Odoo :: 12.0
Classifier: License :: OSI Approved :: GNU Affero General Public License v3
Classifier: Development Status :: 4 - Beta
Requires-Python: >=3.5
Requires-Dist: odoo12-addon-fieldservice
Requires-Dist: odoo <12.1dev,>=12.0a
